AUTHORS.rst
CONTRIBUTING.rst
HISTORY.rst
LICENSE
MANIFEST.in
README.rst
setup.cfg
setup.py
docs/Makefile
docs/authors.rst
docs/conf.py
docs/contributing.rst
docs/history.rst
docs/index.rst
docs/installation.rst
docs/make.bat
docs/readme.rst
docs/usage.rst
ellipt2d/__init__.py
ellipt2d/ellipt2d.py
ellipt2d.egg-info/PKG-INFO
ellipt2d.egg-info/SOURCES.txt
ellipt2d.egg-info/dependency_links.txt
ellipt2d.egg-info/not-zip-safe
ellipt2d.egg-info/top_level.txt
tests/__init__.py
tests/test_ellipt2d.py