Metadata-Version: 1.2
Name: ellipt2d
Version: 2.1.0
Summary: A package to solve second order elliptic problems in 2D
Home-page: https://github.com/pletzer/ellipt2d
Author: Alexander Pletzer
Author-email: alexander@gokliya.net
License: MIT license
Keywords: ellipt2d
Platform: UNKNOWN
Classifier: Development Status :: 2 - Pre-Alpha
Classifier: Intended Audience :: Developers
Classifier: License :: OSI Approved :: MIT License
Classifier: Natural Language :: English
Classifier: Programming Language :: Python :: 3
Classifier: Programming Language :: Python :: 3.5
Classifier: Programming Language :: Python :: 3.6
Classifier: Programming Language :: Python :: 3.7
Classifier: Programming Language :: Python :: 3.8
Requires-Python: >=3.5
